{
  "db_name": "PostgreSQL",
  "query": "\n                INSERT INTO links (\n                    fid,\n                    target_fid,\n                    type,\n                    hash,\n                    timestamp,\n                    deleted_at,\n                    display_timestamp\n                )\n                VALUES ($1, $2, $3, $4, $5, $6, $7)\n                ON CONFLICT (hash) DO UPDATE SET\n                    deleted_at = EXCLUDED.deleted_at,\n                    timestamp = LEAST(EXCLUDED.timestamp, links.timestamp),\n                    display_timestamp = COALESCE(links.display_timestamp, EXCLUDED.display_timestamp)\n                ",
  "describe": {
    "columns": [],
    "parameters": {
      "Left": [
        "Int8",
        "Int8",
        "Text",
        "Bytea",
        "Timestamptz",
        "Timestamptz",
        "Timestamptz"
      ]
    },
    "nullable": []
  },
  "hash": "e246414321272a83d45e72862429449ed6b6d61eea072512e346678681870b00"
}
